{
  "id": "hebrew-lesson-05",
  "name": "Lesson 5 Vocabulary",
  "description": "Vocabulary from Lambdin's Introduction to Biblical Hebrew, Lesson 5.",
  "language": "hbo",
  "cardType": "vocabulary",
  "cards": [
    {
      "category": "nouns",
      "hebrew": "זָהָב",
      "transliteration": "zāhāḇ",
      "definition": "gold"
    },
    {
      "category": "nouns",
      "hebrew": "חָכְמָה",
      "transliteration": "ḥoḵmāh",
      "definition": "wisdom"
    },
    {
      "category": "nouns",
      "hebrew": "כֶּסֶף",
      "transliteration": "késep̄",
      "definition": "silver, money"
    },
    {
      "category": "nouns",
      "hebrew": "עֲבֹדָה",
      "transliteration": "ʿăḇōdāh",
      "definition": "work, task, servitude (cf. ʿéḇed)"
    },
    {
      "category": "nouns",
      "hebrew": "עֵצָה",
      "transliteration": "ʿēṣāh",
      "definition": "counsel, advice"
    },
    {
      "category": "adjectives",
      "hebrew": "יָקָר",
      "transliteration": "yāqār",
      "definition": "precious"
    },
    {
      "category": "adjectives",
      "hebrew": "יָשָׁר",
      "transliteration": "yāšār",
      "definition": "just, upright"
    },
    {
      "category": "adjectives",
      "hebrew": "צַדִּיק",
      "transliteration": "ṣaddîq",
      "definition": "righteous"
    },
    {
      "category": "adjectives",
      "hebrew": "קָשֶׁה",
      "transliteration": "qāšeh",
      "definition": "difficult, hard, harsh"
    },
    {
      "category": "adjectives",
      "hebrew": "רָשָׁע",
      "transliteration": "rāšāʿ",
      "definition": "evil, bad, criminal"
    },
    {
      "category": "proper_names",
      "hebrew": "דָּוִד",
      "transliteration": "Dāwid",
      "definition": "David"
    },
    {
      "category": "proper_names",
      "hebrew": "שְׁמוּאֵל",
      "transliteration": "šəmûʾēl",
      "definition": "Samuel"
    },
    {
      "category": "proper_names",
      "hebrew": "יְרוּשָׁלִַם",
      "transliteration": "Yərûšālaim",
      "definition": "Jerusalem",
      "notes": "Note that in the Hebrew spelling the second י is missing. This spelling may point to an early dialectal variant pronunciation Yərûšālēm"
    },
    {
      "category": "other",
      "hebrew": "מִן",
      "transliteration": "min-",
      "definition": "(prep.) from; also used partitively: מֵהָאֲנָשִׁים mēhāʾănāšîm, some of the men"
    },
    {
      "category": "other",
      "hebrew": "אֲשֶׁר",
      "transliteration": "ʾăšer",
      "definition": "(rel. pronoun) who, which, that"
    }
  ]
}
